mcerrors/__init__.py
mcerrors/core.py
mcerrors-1.0.1.dist-info/LICENSE
mcerrors-1.0.1.dist-info/METADATA
mcerrors-1.0.1.dist-info/WHEEL
mcerrors-1.0.1.dist-info/top_level.txt
mcerrors-1.0.1.dist-info/RECORD
